knu_rl_env/__init__.py
knu_rl_env/agent.py
knu_rl_env/angry_birds/__init__.py
knu_rl_env/angry_birds/characters.py
knu_rl_env/angry_birds/level.py
knu_rl_env/angry_birds/main.py
knu_rl_env/angry_birds/polygon.py
knu_rl_env/frozen_lake/__init__.py
knu_rl_env/frozen_lake/agent.py
knu_rl_env/frozen_lake/env.py
knu_rl_env/grid_adventure/__init__.py
knu_rl_env/grid_adventure/agent.py
knu_rl_env/grid_adventure/bgm.ogg
knu_rl_env/grid_adventure/env.py
knu_rl_env/grid_adventure/grid-adventure.csv
knu_rl_env/grid_adventure/run.py
knu_rl_env/grid_survivor/__init__.py
knu_rl_env/grid_survivor/agent.py
knu_rl_env/grid_survivor/bgm.ogg
knu_rl_env/grid_survivor/env.py
knu_rl_env/grid_survivor/grid-survivor.csv
knu_rl_env/grid_survivor/run.py
knu_rl_env/road_hog/__init__.py
knu_rl_env/road_hog/agent.py
knu_rl_env/road_hog/bgm.ogg
knu_rl_env/road_hog/env.py
knu_rl_env/road_hog/run.py
knu_rl_env-2.3.dist-info/METADATA
knu_rl_env-2.3.dist-info/WHEEL
knu_rl_env-2.3.dist-info/top_level.txt
knu_rl_env-2.3.dist-info/RECORD
