Metadata-Version: 2.1
Name: knu-rl-env
Version: 2.3
Author-email: Woohyeok Choi <woohyeok.choi@kangwon.ac.kr>, Sanghyeon Hwang <shyeon0114@gmail.com>
Maintainer-email: Woohyeok Choi <woohyeok.choi@kangwon.ac.kr>
License: Apache License 2.0
Project-URL: Homepage, https://knu-p4c-lab.github.io/
Classifier: Programming Language :: Python :: 3
Classifier: Programming Language :: Python :: 3.10
Classifier: Programming Language :: Python :: 3.11
Classifier: Programming Language :: Python :: 3.12
Requires-Python: >=3.10
Requires-Dist: gymnasium==1.0.0
Requires-Dist: pygame==2.6.1
Requires-Dist: minigrid==2.3.1
Requires-Dist: numpy>=2.1.2
Requires-Dist: highway-env==1.10.1
